datapro/__init__.py
datapro/base/__init__.py
datapro/base/interface.py
datapro/base/util.py
datapro/core/__init__.py
datapro/core/db.py
datapro/core/job.py
datapro/core/tool.py
datapro/core/validation.py
datapro/core/model/__init__.py
datapro/core/model/admin.py
datapro/core/model/common.py
datapro/core/model/init.py
datapro-0.1.1.dist-info/DESCRIPTION.rst
datapro-0.1.1.dist-info/METADATA
datapro-0.1.1.dist-info/RECORD
datapro-0.1.1.dist-info/WHEEL
datapro-0.1.1.dist-info/entry_points.txt
datapro-0.1.1.dist-info/metadata.json
datapro-0.1.1.dist-info/top_level.txt
