Metadata-Version: 2.0
Name: datapro
Version: 0.1.1
Summary: Data processing libraries written in Python
Home-page: https://github.com/jelloslinger/datapro
Author: Michael Copeland
Author-email: michael.james.copeland@gmail.com
License: MIT
Requires-Dist: SQLAlchemy
Requires-Dist: pytz
Requires-Dist: xlrd
Requires-Dist: xlwt
Provides-Extra: dev
Requires-Dist: check-manifest; extra == 'dev'
Provides-Extra: test
Requires-Dist: coverage; extra == 'test'
